README.rst
setup.py
usfm_tools_py3/__init__.py
usfm_tools_py3/transform.py
usfm_tools_py3.egg-info/PKG-INFO
usfm_tools_py3.egg-info/SOURCES.txt
usfm_tools_py3.egg-info/dependency_links.txt
usfm_tools_py3.egg-info/requires.txt
usfm_tools_py3.egg-info/top_level.txt
usfm_tools_py3/support/__init__.py
usfm_tools_py3/support/abstractRenderer.py
usfm_tools_py3/support/asciiRenderer.py
usfm_tools_py3/support/books.py
usfm_tools_py3/support/contextRenderer.py
usfm_tools_py3/support/csvRenderer.py
usfm_tools_py3/support/htmlRenderer.py
usfm_tools_py3/support/loutRenderer.py
usfm_tools_py3/support/mdRenderer.py
usfm_tools_py3/support/mediawikiPrinter.py
usfm_tools_py3/support/oldhtmlRenderer.py
usfm_tools_py3/support/parseUsfm.py
usfm_tools_py3/support/readerise.py
usfm_tools_py3/support/singlehtmlRenderer.py
usfm_tools_py3/support/usxRenderer.py