Metadata-Version: 1.0
Name: usfm-tools-py3
Version: 0.0.28
Summary: A framework for transforming .usfm files into specified targets
Home-page: https://github.com/unfoldingWord-dev/USFM-Tools
Author: unfoldingWord
Author-email: info@unfoldingWord.org
License: MIT
Keywords: unfoldingWord usfm tools
Platform: UNKNOWN
